Workbook

Sheet OFFRE
B10: ="OFFER N° : "&FORMULAIRE!$B$2 -> OFFER N° : DE26464 | J10: =FORMULAIRE!$B$9&CHAR(10)&CHAR(10)&FORMULAIRE!$B$10&CHAR(10)&FORMULAIRE!$B$11&CHAR(10)&FORMULAIRE!$B$12 -> INTELS NIGERIA LIMITED ONNE OIL & GAS FREEZONE ONNE RIVERS STATE NIGERIA - NIGERIA
B13: =FORMULAIRE!$B$3&", "&TEXT(FORMULAIRE!$B$4,"dd/mm/yyyy") -> Lagos, 25/06/2026
B15: To the attention of : | D15: =FORMULAIRE!$B$5 -> Mr. ANTHONY IBIDIGBA | E15: =FORMULAIRE!$B$5 -> Mr. ANTHONY IBIDIGBA
B16: Machine : | D16: =FORMULAIRE!$B$6 -> RT555 s/n 161606 | E16: =FORMULAIRE!$B$6 -> RT555 s/n 161606
B17: Client Code : | D17: =FORMULAIRE!$B$7 -> 270251 | E17: =FORMULAIRE!$B$7 -> 270251
B19: Reference | D19: Designation | I19: Qty | J19: Avail | K19: Unit Price | M19: Discount | N19: Discounted Unit Price | P19: Total
B20: =IF(FORMULAIRE!$A$21="","",FORMULAIRE!$A$21) -> T135335 | D20: =IF(FORMULAIRE!$A$21="","",FORMULAIRE!$B$21) -> COMPUTER, RCL W/ DATALOGGER REPLACES P/N T107350 | I20: =IF(FORMULAIRE!$A$21="","",FORMULAIRE!$C$21) -> 1 | J20: =IF(FORMULAIRE!$A$21="","",FORMULAIRE!$D$21) -> Imm | K20: =IF(FORMULAIRE!$A$21="","",FORMULAIRE!$E$21) -> 11844 | M20: =IF(FORMULAIRE!$A$21="","",FORMULAIRE!$F$21) -> 0.2 | N20: =IF(FORMULAIRE!$A$21="","",FORMULAIRE!$G$21) -> 9475.2 | P20: =IF(FORMULAIRE!$A$21="","",FORMULAIRE!$H$21) -> 9475.2
B21: =IF(FORMULAIRE!$A$22="","",FORMULAIRE!$A$22) -> TRANSP | D21: =IF(FORMULAIRE!$A$22="","",FORMULAIRE!$B$22) -> Air freight option incoterms CIF PORT HARCOURT, NIGERIA – optional | I21: =IF(FORMULAIRE!$A$22="","",FORMULAIRE!$C$22) -> 1 | J21: =IF(FORMULAIRE!$A$22="","",FORMULAIRE!$D$22) -> 10D | K21: =IF(FORMULAIRE!$A$22="","",FORMULAIRE!$E$22) -> 900 | M21: =IF(FORMULAIRE!$A$22="","",FORMULAIRE!$F$22) -> 0 | N21: =IF(FORMULAIRE!$A$22="","",FORMULAIRE!$G$22) -> 900 | P21: =IF(FORMULAIRE!$A$22="","",FORMULAIRE!$H$22) -> 900
B22: =IF(FORMULAIRE!$A$23="","",FORMULAIRE!$A$23) | D22: =IF(FORMULAIRE!$A$23="","",FORMULAIRE!$B$23) | I22: =IF(FORMULAIRE!$A$23="","",FORMULAIRE!$C$23) | J22: =IF(FORMULAIRE!$A$23="","",FORMULAIRE!$D$23) | K22: =IF(FORMULAIRE!$A$23="","",FORMULAIRE!$E$23) | M22: =IF(FORMULAIRE!$A$23="","",FORMULAIRE!$F$23) | N22: =IF(FORMULAIRE!$A$23="","",FORMULAIRE!$G$23) | P22: =IF(FORMULAIRE!$A$23="","",FORMULAIRE!$H$23)
B23: =IF(FORMULAIRE!$A$24="","",FORMULAIRE!$A$24) | D23: =IF(FORMULAIRE!$A$24="","",FORMULAIRE!$B$24) | I23: =IF(FORMULAIRE!$A$24="","",FORMULAIRE!$C$24) | J23: =IF(FORMULAIRE!$A$24="","",FORMULAIRE!$D$24) | K23: =IF(FORMULAIRE!$A$24="","",FORMULAIRE!$E$24) | M23: =IF(FORMULAIRE!$A$24="","",FORMULAIRE!$F$24) | N23: =IF(FORMULAIRE!$A$24="","",FORMULAIRE!$G$24) | P23: =IF(FORMULAIRE!$A$24="","",FORMULAIRE!$H$24)
B24: =IF(FORMULAIRE!$A$25="","",FORMULAIRE!$A$25) | D24: =IF(FORMULAIRE!$A$25="","",FORMULAIRE!$B$25) | I24: =IF(FORMULAIRE!$A$25="","",FORMULAIRE!$C$25) | J24: =IF(FORMULAIRE!$A$25="","",FORMULAIRE!$D$25) | K24: =IF(FORMULAIRE!$A$25="","",FORMULAIRE!$E$25) | M24: =IF(FORMULAIRE!$A$25="","",FORMULAIRE!$F$25) | N24: =IF(FORMULAIRE!$A$25="","",FORMULAIRE!$G$25) | P24: =IF(FORMULAIRE!$A$25="","",FORMULAIRE!$H$25)
B25: =IF(FORMULAIRE!$A$26="","",FORMULAIRE!$A$26) | D25: =IF(FORMULAIRE!$A$26="","",FORMULAIRE!$B$26) | I25: =IF(FORMULAIRE!$A$26="","",FORMULAIRE!$C$26) | J25: =IF(FORMULAIRE!$A$26="","",FORMULAIRE!$D$26) | K25: =IF(FORMULAIRE!$A$26="","",FORMULAIRE!$E$26) | M25: =IF(FORMULAIRE!$A$26="","",FORMULAIRE!$F$26) | N25: =IF(FORMULAIRE!$A$26="","",FORMULAIRE!$G$26) | P25: =IF(FORMULAIRE!$A$26="","",FORMULAIRE!$H$26)
B26: =IF(FORMULAIRE!$A$27="","",FORMULAIRE!$A$27) | D26: =IF(FORMULAIRE!$A$27="","",FORMULAIRE!$B$27) | I26: =IF(FORMULAIRE!$A$27="","",FORMULAIRE!$C$27) | J26: =IF(FORMULAIRE!$A$27="","",FORMULAIRE!$D$27) | K26: =IF(FORMULAIRE!$A$27="","",FORMULAIRE!$E$27) | M26: =IF(FORMULAIRE!$A$27="","",FORMULAIRE!$F$27) | N26: =IF(FORMULAIRE!$A$27="","",FORMULAIRE!$G$27) | P26: =IF(FORMULAIRE!$A$27="","",FORMULAIRE!$H$27)
B27: =IF(FORMULAIRE!$A$28="","",FORMULAIRE!$A$28) | D27: =IF(FORMULAIRE!$A$28="","",FORMULAIRE!$B$28) | I27: =IF(FORMULAIRE!$A$28="","",FORMULAIRE!$C$28) | J27: =IF(FORMULAIRE!$A$28="","",FORMULAIRE!$D$28) | K27: =IF(FORMULAIRE!$A$28="","",FORMULAIRE!$E$28) | M27: =IF(FORMULAIRE!$A$28="","",FORMULAIRE!$F$28) | N27: =IF(FORMULAIRE!$A$28="","",FORMULAIRE!$G$28) | P27: =IF(FORMULAIRE!$A$28="","",FORMULAIRE!$H$28)
D28: ="Account Name: "&FORMULAIRE!$B$31&CHAR(10)&"Number: "&FORMULAIRE!$B$32&CHAR(10)&"BENEFICIARY BANK: "&FORMULAIRE!$B$33&CHAR(10)&"SWIFT CODE: "&FORMULAIRE!$B$34&CHAR(10)&"SORT CODE: "&FORMULAIRE!$B$35 -> Account Name: WESTCHASE OIL AND GAS LTD Number: USD ACCOUNT NO : 5250152975 BENEFICIARY BANK: FIDELITY BANK PLC SWIFT CODE: CITIUS33 SORT CODE: FIDTNGLA
K35: TOTAL | N35: VAT | P35: TOTAL w/ VAT
B36: Payment Terms : | D36: =FORMULAIRE!$B$14 -> Advance payment | F36: =FORMULAIRE!$B$14 -> Advance payment | K36: =SUM(FORMULAIRE!$H$21:$H$28) -> 10375.2 | N36: =IF(FORMULAIRE!$B$18=0,"",SUM(FORMULAIRE!$H$21:$H$28)*FORMULAIRE!$B$18) | P36: =SUM(FORMULAIRE!$H$21:$H$28)*(1+FORMULAIRE!$B$18) -> 10375.2
B37: Validity of Offer : | D37: =FORMULAIRE!$B$15 -> 30 Days | F37: =FORMULAIRE!$B$15 -> 30 Days
B38: Delivery Terms : | D38: =FORMULAIRE!$B$16 -> CIF, Port Harcourt | F38: =FORMULAIRE!$B$16 -> CIF, Port Harcourt
B39: Currency : | D39: =FORMULAIRE!$B$17 -> USD | F39: =FORMULAIRE!$B$17 -> USD
B42: Contractual Document:
B44: The availability date is indicative and will be confirmed upon ordering, unless the item is sold in the meantime.
B45: Please refer to the attached terms and conditions of sale.
B46: We are at your disposal for any further information
B48: Sincerely,
B53: =FORMULAIRE!$B$37 -> WESTCHASE OIL & GAS – 11, Sumbo Jibowu Ikoyi, Lagos, Lagos, Nigeria
B54: =FORMULAIRE!$B$38 -> Tél. : +234 814 315 5517 - vematwestchase @vematgroup.com
B55: =FORMULAIRE!$B$39 -> Vemat Westchase LTD is an authorized distributor of TEREX RT CRANES, TADANO, JLG, MAGNI, INGERSOLL RAND, and MECALAC products

Sheet FORMULAIRE
A1: FORMULAIRE DE SAISIE - OFFRE WESTCHASE
A2: OFFER N° | B2: DE26464
A3: Ville | B3: Lagos
A4: Date | B4: 46198
A5: To the attention of | B5: Mr. ANTHONY IBIDIGBA
A6: Machine | B6: RT555 s/n 161606
A7: Client Code | B7: 270251
A9: Client - Ligne 1 | B9: INTELS NIGERIA LIMITED
A10: Client - Ligne 2 | B10: ONNE OIL & GAS FREEZONE
A11: Client - Ligne 3 | B11: ONNE RIVERS STATE
A12: Client - Ligne 4 | B12: NIGERIA - NIGERIA
A14: Payment Terms | B14: Advance payment
A15: Validity of Offer | B15: 30 Days
A16: Delivery Terms | B16: CIF, Port Harcourt
A17: Currency | B17: USD
A18: VAT Rate | B18: 0
A20: Reference | B20: Designation | C20: Qty | D20: Avail | E20: Unit Price | F20: Discount | G20: Discounted Unit Price | H20: Total
A21: T135335 | B21: COMPUTER, RCL W/ DATALOGGER REPLACES P/N T107350 | C21: 1 | D21: Imm | E21: 11844 | F21: 0.2 | G21: =IF(A21="","",E21*(1-F21)) -> 9475.2 | H21: =IF(A21="","",C21*G21) -> 9475.2
A22: TRANSP | B22: Air freight option incoterms CIF PORT HARCOURT, NIGERIA – optional | C22: 1 | D22: 10D | E22: 900 | F22: 0 | G22: =IF(A22="","",E22*(1-F22)) -> 900 | H22: =IF(A22="","",C22*G22) -> 900
G23: =IF(A23="","",E23*(1-F23)) | H23: =IF(A23="","",C23*G23)
G24: =IF(A24="","",E24*(1-F24)) | H24: =IF(A24="","",C24*G24)
G25: =IF(A25="","",E25*(1-F25)) | H25: =IF(A25="","",C25*G25)
G26: =IF(A26="","",E26*(1-F26)) | H26: =IF(A26="","",C26*G26)
G27: =IF(A27="","",E27*(1-F27)) | H27: =IF(A27="","",C27*G27)
G28: =IF(A28="","",E28*(1-F28)) | H28: =IF(A28="","",C28*G28)
A31: Account Name | B31: WESTCHASE OIL AND GAS LTD
A32: Number | B32: USD ACCOUNT NO : 5250152975
A33: BENEFICIARY BANK | B33: FIDELITY BANK PLC
A34: SWIFT CODE | B34: CITIUS33
A35: SORT CODE | B35: FIDTNGLA
A37: Footer line 1 | B37: WESTCHASE OIL & GAS – 11, Sumbo Jibowu Ikoyi, Lagos, Lagos, Nigeria
A38: Footer line 2 | B38: Tél. : +234 814 315 5517 - vematwestchase @vematgroup.com
A39: Footer line 3 | B39: Vemat Westchase LTD is an authorized distributor of TEREX RT CRANES, TADANO, JLG, MAGNI, INGERSOLL RAND, and MECALAC products
